{
	"name": "Developir Theme",
	"type": "light",
	"colors": {
		"foreground": "#444444",
		"focusBorder": "#245ed1",
		"selection.background": "#b0daff",
		"scrollbar.shadow": "#dddddd",
		"activityBar.foreground": "#245ed1",
		"activityBar.background": "#ffffff",
		"activityBar.inactiveForeground": "#a5a5a5",
		"activityBarBadge.foreground": "#ffffff",
		"activityBarBadge.background": "#245ed1",
		"activityBar.border": "#e0e4e8",
		"activityBar.activeBackground": "#ffffff00",
		"sideBar.background": "#f6f8fa",
		"sideBar.foreground": "#444444",
		"sideBarSectionHeader.background": "#f6f8fa",
		"sideBarSectionHeader.foreground": "#000000",
		"sideBarSectionHeader.border": "#e0e4e8",
		"sideBarTitle.foreground": "#245ed1",
		"sideBar.border": "#e0e4e8",
		"list.inactiveSelectionBackground": "#e0e4e8",
		"list.inactiveSelectionForeground": "#000000",
		"list.hoverBackground": "#e0e4e8",
		"list.hoverForeground": "#000000",
		"list.activeSelectionBackground": "#245ed1",
		"list.activeSelectionForeground": "#ffffff",
		"tree.indentGuidesStroke": "#e0e4e8",
		"list.dropBackground": "#d5f9ff",
		"list.highlightForeground": "#0066bf",
		"list.focusBackground": "#d6ebff",
		"list.focusForeground": "#616161",
		"listFilterWidget.background": "#efc1ad",
		"listFilterWidget.outline": "#00000000",
		"listFilterWidget.noMatchesOutline": "#be1100",
		"statusBar.foreground": "#ffffff",
		"statusBar.background": "#245ed1",
		"statusBarItem.hoverBackground": "#ffffff1f",
		"statusBar.border": "#245ed1",
		"statusBar.debuggingBackground": "#245ed1",
		"statusBar.debuggingForeground": "#ffffff",
		"statusBar.debuggingBorder": "#245ed1",
		"statusBar.noFolderBackground": "#245ed1",
		"statusBar.noFolderForeground": "#ffffff",
		"statusBar.noFolderBorder": "#245ed1",
		"statusBarItem.remoteBackground": "#245ed1",
		"statusBarItem.remoteForeground": "#ffffff",
		"titleBar.activeBackground": "#ffffff",
		"titleBar.activeForeground": "#444444",
		"titleBar.inactiveBackground": "#f6f8fa",
		"titleBar.inactiveForeground": "#a5a5a5",
		"titleBar.border": "#e0e4e8",
		"menubar.selectionForeground": "#000000",
		"menubar.selectionBackground": "#0000001a",
		"menubar.selectionBorder": "#e0e4e8",
		"menu.foreground": "#444444",
		"menu.background": "#ffffff",
		"menu.selectionForeground": "#ffffff",
		"menu.selectionBackground": "#245ed1",
		"menu.selectionBorder": "#245ed1",
		"menu.separatorBackground": "#e0e4e8",
		"menu.border": "#e0e4e8",
		"button.background": "#245ed1",
		"button.foreground": "#ffffff",
		"button.hoverBackground": "#000000",
		"button.secondaryForeground": "#ffffff",
		"button.secondaryBackground": "#2d6faa",
		"button.secondaryHoverBackground": "#000000",
		"input.background": "#ffffff",
		"input.border": "#e0e4e8",
		"input.foreground": "#444444",
		"inputOption.activeBackground": "#245ed1",
		"inputOption.activeBorder": "#245ed1",
		"inputOption.activeForeground": "#ffffff",
		"input.placeholderForeground": "#a5a5a5",
		"textLink.foreground": "#245ed1",
		"editor.background": "#ffffff",
		"editor.foreground": "#444444",
		"editorLineNumber.foreground": "#a5a5a5",
		"editorCursor.foreground": "#444444",
		"editorCursor.background": "#ffffff",
		"editor.selectionBackground": "#dcf4fd",
		"editor.inactiveSelectionBackground": "#dcf4fd",
		"editorWhitespace.foreground": "#e0e4e8",
		"editor.selectionHighlightBackground": "#dcf4fd",
		"editor.selectionHighlightBorder": "#01b0f0",
		"editor.findMatchBackground": "#dcf4fd",
		"editor.findMatchBorder": "#01b0f0",
		"editor.findMatchHighlightBackground": "#dcf4fd",
		"editor.findMatchHighlightBorder": "#dcf4fd",
		"editor.findRangeHighlightBackground": "#f6f8fa",
		"editor.findRangeHighlightBorder": "#ffffff00",
		"editor.rangeHighlightBackground": "#dcf4fd",
		"editor.rangeHighlightBorder": "#ffffff00",
		"editor.hoverHighlightBackground": "#dcf4fd",
		"editor.wordHighlightStrongBackground": "#dcf4fd",
		"editor.wordHighlightStrongBorder": "#00000000",
		"editor.wordHighlightBackground": "#dcf4fd",
		"editor.wordHighlightBorder": "#00000000",
		"editor.lineHighlightBackground": "#f6f8fa",
		"editor.lineHighlightBorder": "#ffffff00",
		"editorLineNumber.activeForeground": "#444444",
		"editorLink.activeForeground": "#245ed1",
		"editorIndentGuide.background1": "#0000000e",
		"editorIndentGuide.activeBackground1": "#e0e4e8",
		"editorRuler.foreground": "#ffffff00",
		"editorBracketMatch.background": "#dcf4fd",
		"editorBracketMatch.border": "#01b0f0",
		"editor.foldBackground": "#dcf4fd",
		"editorOverviewRuler.background": "#f6f8fa",
		"editorOverviewRuler.border": "#f6f8fa",
		"editorError.foreground": "#e20505",
		"editorError.background": "#e2050516",
		"editorError.border": "#e2050500",
		"editorWarning.foreground": "#ff9500",
		"editorWarning.background": "#ffcb0022",
		"editorWarning.border": "#ffffff00",
		"editorInfo.foreground": "#43afdd",
		"editorInfo.background": "#1aeaff26",
		"editorInfo.border": "#4490BF00",
		"editorGutter.background": "#ffffff",
		"editorGutter.modifiedBackground": "#43afdd",
		"editorGutter.addedBackground": "#1d990a",
		"editorGutter.deletedBackground": "#e20505",
		"editorGutter.foldingControlForeground": "#a5a5a5",
		"editorCodeLens.foreground": "#a5a5a5",
		"editorGroup.border": "#e0e4e8",
		"diffEditor.insertedTextBackground": "#59ff5c3a",
		"diffEditor.insertedTextBorder": "#68ff0000",
		"diffEditor.removedTextBackground": "#ff352b1a",
		"diffEditor.removedTextBorder": "#ff000000",
		"diffEditor.border": "#8a6565",
		"panel.background": "#ffffff",
		"panel.border": "#e0e4e8",
		"panelTitle.activeBorder": "#424242",
		"panelTitle.activeForeground": "#245ed1",
		"panelTitle.inactiveForeground": "#a5a5a5",
		"badge.background": "#e0e4e8",
		"badge.foreground": "#444444",
		"terminal.foreground": "#444444",
		"terminal.selectionBackground": "#77e5ff40",
		"terminalCursor.background": "#000000",
		"terminalCursor.foreground": "#ffffff",
		"terminal.border": "#e0e4e8",
		"terminal.ansiBlack": "#111111",
		"terminal.ansiBlue": "#245ed1",
		"terminal.ansiBrightBlack": "#666666",
		"terminal.ansiBrightBlue": "#245ed1",
		"terminal.ansiBrightCyan": "#43afdd",
		"terminal.ansiBrightGreen": "#14ce14",
		"terminal.ansiBrightMagenta": "#7030a0",
		"terminal.ansiBrightRed": "#e20505",
		"terminal.ansiBrightWhite": "#a5a5a5",
		"terminal.ansiBrightYellow": "#ff9500",
		"terminal.ansiCyan": "#43afdd",
		"terminal.ansiGreen": "#1d990a",
		"terminal.ansiMagenta": "#7030a0",
		"terminal.ansiRed": "#e20505",
		"terminal.ansiWhite": "#a5a5a5",
		"terminal.ansiYellow": "#ff9500",
		"breadcrumb.background": "#ffffff",
		"breadcrumb.foreground": "#a5a5a5",
		"breadcrumb.focusForeground": "#444444",
		"editorGroupHeader.tabsBackground": "#f6f8fa",
		"editorGroupHeader.tabsBorder": "#e0e4e8",
		"tab.activeForeground": "#444444",
		"tab.border": "#e0e4e8",
		"tab.activeBackground": "#ffffff",
		"tab.activeBorder": "#ffffff",
		"tab.activeBorderTop": "#245ed1",
		"tab.inactiveBackground": "#f6f8fa",
		"tab.inactiveForeground": "#444444",
		"tab.hoverBackground": "#ffffff",
		"tab.hoverForeground": "#444444",
		"scrollbarSlider.background": "#64646466",
		"scrollbarSlider.hoverBackground": "#646464b3",
		"scrollbarSlider.activeBackground": "#00000099",
		"progressBar.background": "#245ed1",
		"widget.shadow": "#00000029",
		"editorWidget.foreground": "#444444",
		"editorWidget.background": "#f6f8fa",
		"editorWidget.resizeBorder": "#e0e4e8",
		"pickerGroup.border": "#e0e4e8",
		"pickerGroup.foreground": "#444444",
		"debugToolBar.background": "#f6f8fa",
		"debugToolBar.border": "#e0e4e8",
		"notifications.foreground": "#616161",
		"notifications.background": "#f6f8fa",
		"notificationToast.border": "#e0e4e8",
		"notificationsErrorIcon.foreground": "#e20505",
		"notificationsWarningIcon.foreground": "#e9a700",
		"notificationsInfoIcon.foreground": "#43afdd",
		"notificationCenter.border": "#e0e4e8",
		"notificationCenterHeader.foreground": "#000000",
		"notificationCenterHeader.background": "#f6f8fa",
		"notifications.border": "#e0e4e8",
		"gitDecoration.addedResourceForeground": "#1d990a",
		"gitDecoration.conflictingResourceForeground": "#7030a0",
		"gitDecoration.deletedResourceForeground": "#e20505",
		"gitDecoration.ignoredResourceForeground": "#a5a5a5",
		"gitDecoration.modifiedResourceForeground": "#a05a48",
		"gitDecoration.stageDeletedResourceForeground": "#e20505",
		"gitDecoration.stageModifiedResourceForeground": "#a05a48",
		"gitDecoration.submoduleResourceForeground": "#43afdd",
		"gitDecoration.untrackedResourceForeground": "#2d6faa",
		"editorMarkerNavigation.background": "#ffffff",
		"editorMarkerNavigationError.background": "#e51400",
		"editorMarkerNavigationWarning.background": "#e9a700",
		"editorMarkerNavigationInfo.background": "#75beff",
		"merge.currentHeaderBackground": "#A4E3D6",
		"merge.currentContentBackground": "#DBF4EF",
		"merge.incomingHeaderBackground": "#A6CFFF",
		"merge.incomingContentBackground": "#DBECFF",
		"merge.commonHeaderBackground": "#BFBFBF",
		"merge.commonContentBackground": "#E5E5E5",
		"editorSuggestWidget.background": "#f3f3f3",
		"editorSuggestWidget.border": "#c8c8c8",
		"editorSuggestWidget.foreground": "#000000",
		"editorSuggestWidget.highlightForeground": "#0066bf",
		"editorSuggestWidget.selectedBackground": "#d6ebff",
		"editorHoverWidget.foreground": "#616161",
		"editorHoverWidget.background": "#f3f3f3",
		"editorHoverWidget.border": "#c8c8c8",
		"peekView.border": "#e0e4e8",
		"peekViewEditor.background": "#f6f8fa",
		"peekViewEditorGutter.background": "#f6f8fa",
		"peekViewEditor.matchHighlightBackground": "#dcf4fd",
		"peekViewEditor.matchHighlightBorder": "#01b0f0",
		"peekViewResult.background": "#f6f8fa",
		"peekViewResult.fileForeground": "#444444",
		"peekViewResult.lineForeground": "#01b0f0",
		"peekViewResult.matchHighlightBackground": "#dcf4fd",
		"peekViewResult.selectionBackground": "#dcf4fd",
		"peekViewResult.selectionForeground": "#01b0f0",
		"peekViewTitle.background": "#ffffff",
		"peekViewTitleDescription.foreground": "#a5a5a5",
		"peekViewTitleLabel.foreground": "#444444",
		"icon.foreground": "#444444",
		"checkbox.background": "#ffffff",
		"checkbox.foreground": "#444444",
		"checkbox.border": "#e0e4e8",
		"dropdown.background": "#ffffff",
		"dropdown.foreground": "#444444",
		"dropdown.border": "#e0e4e8",
		"minimapGutter.addedBackground": "#1d990a",
		"minimapGutter.modifiedBackground": "#43afdd",
		"minimapGutter.deletedBackground": "#e20505",
		"minimap.findMatchHighlight": "#dcf4fd",
		"minimap.selectionHighlight": "#dcf4fd",
		"minimap.errorHighlight": "#e20505",
		"minimap.warningHighlight": "#ff9500",
		"minimap.background": "#ffffff",
		"sideBar.dropBackground": "#d5f9ff",
		"editorGroup.emptyBackground": "#ffffff",
		"panelSection.border": "#e0e4e8",
		"statusBarItem.activeBackground": "#FFFFFF25",
		"settings.headerForeground": "#444444",
		"settings.focusedRowBackground": "#ffffff07",
		"walkThrough.embeddedEditorBackground": "#00000050",
		"breadcrumb.activeSelectionForeground": "#444444",
		"editorGutter.commentRangeForeground": "#a5a5a5",
		"debugExceptionWidget.background": "#f6f8fa",
		"debugExceptionWidget.border": "#e0e4e8"
	},
	"semanticHighlighting": true,
	"semanticTokenColors": {
		
	},
	"tokenColors": [

	]
}
